{"GlobalPropertiesHash":"V5/bhEchzkyUxZg0qX2VNEttNoFFkZAZ3EjditF7rkU=","FingerprintPatternsHash":"gq3WsqcKBUGTSNle7RKKyXRIwh7M8ccEqOqYvIzoM04=","PropertyOverridesHash":"8ZRc1sGeVrPBx4lD717BgRaQekyh78QKV9SKsdt638U=","InputHashes":["z/Uq84Qqwbgdrmm32sn\u002BD47oVQNCFHioW/kBNbcq0cs=","d9I6rTb1I3lzf1GInGS094DDYjxr7vhQQlx0sEfQpP4=","ToCWs5xDiLTfHsS91oJeuMXTP27PBVjET3PvrxGXIAg="],"CachedAssets":{"z/Uq84Qqwbgdrmm32sn\u002BD47oVQNCFHioW/kBNbcq0cs=":{"Identity":"/Users/joshuakabel/Documents/Source/c#/QuestBoard/src/QuestBoard.Api/wwwroot/index.html","SourceId":"QuestBoard.Api","SourceType":"Discovered","ContentRoot":"/Users/joshuakabel/Documents/Source/c#/QuestBoard/src/QuestBoard.Api/wwwroot/","BasePath":"/","RelativePath":"index#[.{fingerprint}]?.html","AssetKind":"All","AssetMode":"All","AssetRole":"Primary","AssetMergeBehavior":null,"AssetMergeSource":"","RelatedAsset":null,"AssetTraitName":null,"AssetTraitValue":null,"Fingerprint":"fqyj6y7drq","Integrity":"aYvIcUCiCw78dojkUqcWiRnBv52k5raBBI1vD01HAdM=","CopyToOutputDirectory":"Never","CopyToPublishDirectory":"PreserveNewest","OriginalItemSpec":"wwwroot/index.html","FileLength":26706,"LastWriteTime":"2026-03-25T11:17:51.0099107+00:00"}},"CachedCopyCandidates":{}}